pangadfs/__init__.py
pangadfs/base.py
pangadfs/crossover.py
pangadfs/fitness.py
pangadfs/ga.py
pangadfs/misc.py
pangadfs/mutate.py
pangadfs/optimize.py
pangadfs/penalty.py
pangadfs/pool.py
pangadfs/populate.py
pangadfs/pospool.py
pangadfs/select.py
pangadfs/validate.py
pangadfs/app/__init__.py
pangadfs/app/app.py
pangadfs-0.1.1.dist-info/LICENSE
pangadfs-0.1.1.dist-info/METADATA
pangadfs-0.1.1.dist-info/WHEEL
pangadfs-0.1.1.dist-info/entry_points.txt
pangadfs-0.1.1.dist-info/top_level.txt
pangadfs-0.1.1.dist-info/RECORD
